micnet/__init__.py
micnet/kombucha.py
micnet/utils.py
micnet/data/kombucha_data.txt
micnet/network/__init__.py
micnet/network/network_core.py
micnet/network/plots.py
micnet/network/relationships.py
micnet/network/subnetwork.py
micnet/network/utils.py
micnet/sparcc/Compute_SparCC.py
micnet/sparcc/General_Core.py
micnet/sparcc/General_Execution.py
micnet/sparcc/MakeBootstraps.py
micnet/sparcc/PseudoPvals.py
micnet/sparcc/__init__.py
micnet/sparcc/core/SparCC.py
micnet/sparcc/core/__init__.py
micnet/sparcc/core/args.py
micnet/sparcc/core/compositional_methods.py
micnet/sparcc/core/core_methods.py
micnet/sparcc/core/io_methods.py
micnet/sparcc/core/logger.py
micnet/sparcc/core/util.py
micnet/sparcc/tests/__init__.py
micnet/sparcc/tests/test_SparCC.py
micnet/sparcc/tests/test_compositional_methods.py
micnet/sparcc/tests/test_core_methods.py
micnet/visualization/__init__.py
micnet/visualization/umap_hdbscan.py
micnet-1.0.0.dist-info/METADATA
micnet-1.0.0.dist-info/WHEEL
micnet-1.0.0.dist-info/top_level.txt
micnet-1.0.0.dist-info/RECORD
