Metadata-Version: 2.1
Name: micnet
Version: 1.0.0
Summary: Toolbox for the visualization and analysis of microbial datasets
Home-page: UNKNOWN
Author: Natalia Favila, David Madrigal-Trejo, Daniel Legorreta
Author-email: natalia.favila.v@gmail.com
License: UNKNOWN
Platform: UNKNOWN
Classifier: Intended Audience :: Education
Classifier: Programming Language :: Python :: 3
